{
    "1.0": {
        "packet_latency": {
            "avg": 298.655,
            "min": 48.0,
            "max": 48.0
        },
        "network_latency": {
            "avg": 298.655,
            "min": 48.0,
            "max": 48.0
        },
        "flit_latency": {
            "avg": 286.334,
            "min": 48.0,
            "max": 48.0
        },
        "fragmentation": {
            "avg": 23.4789,
            "min": 0.0,
            "max": 0.0
        },
        "injected_packet_rate": {
            "avg": 9.015e-05,
            "min": 0.0,
            "max": 0.0
        },
        "accepted_packet_rate": {
            "avg": 9.0125e-05,
            "min": 0.0,
            "max": 0.0
        },
        "injected_flit_rate": {
            "avg": 0.00041225,
            "min": 0.0,
            "max": 0.0
        },
        "accepted_flit_rate": {
            "avg": 0.000412125,
            "min": 0.0,
            "max": 0.0
        },
        "injected_packet_size": {
            "avg": 4.57293
        },
        "accepted_packet_size": {
            "avg": 4.57282
        },
        "hops": {
            "avg": 8.23745
        },
        "total_run_time_cycles": 1000000.0,
        "total_run_time": 712.604
    }
}