{
    "1.0": {
        "packet_latency": {
            "avg": 274.931,
            "min": 13.0,
            "max": 13.0
        },
        "network_latency": {
            "avg": 274.925,
            "min": 13.0,
            "max": 13.0
        },
        "flit_latency": {
            "avg": 271.141,
            "min": 13.0,
            "max": 13.0
        },
        "fragmentation": {
            "avg": 17.2781,
            "min": 0.0,
            "max": 0.0
        },
        "injected_packet_rate": {
            "avg": 0.00237525,
            "min": 0.0,
            "max": 0.0
        },
        "accepted_packet_rate": {
            "avg": 0.00237443,
            "min": 0.0,
            "max": 0.0
        },
        "injected_flit_rate": {
            "avg": 0.00818035,
            "min": 0.0,
            "max": 0.0
        },
        "accepted_flit_rate": {
            "avg": 0.00817741,
            "min": 0.0,
            "max": 0.0
        },
        "injected_packet_size": {
            "avg": 3.444
        },
        "accepted_packet_size": {
            "avg": 3.44395
        },
        "hops": {
            "avg": 7.42371
        },
        "total_run_time_cycles": 1000000.0,
        "total_run_time": 327.184
    }
}