{
    "1.0": {
        "packet_latency": {
            "avg": 166.872,
            "min": 48.0,
            "max": 48.0
        },
        "network_latency": {
            "avg": 166.872,
            "min": 48.0,
            "max": 48.0
        },
        "flit_latency": {
            "avg": 154.043,
            "min": 48.0,
            "max": 48.0
        },
        "fragmentation": {
            "avg": 24.8356,
            "min": 0.0,
            "max": 0.0
        },
        "injected_packet_rate": {
            "avg": 0.000183775,
            "min": 0.0,
            "max": 0.0
        },
        "accepted_packet_rate": {
            "avg": 0.000183675,
            "min": 0.0,
            "max": 0.0
        },
        "injected_flit_rate": {
            "avg": 0.000883575,
            "min": 0.0,
            "max": 0.0
        },
        "accepted_flit_rate": {
            "avg": 0.000882875,
            "min": 0.0,
            "max": 0.0
        },
        "injected_packet_size": {
            "avg": 4.80792
        },
        "accepted_packet_size": {
            "avg": 4.80672
        },
        "hops": {
            "avg": 4.54199
        },
        "total_run_time_cycles": 1000000.0,
        "total_run_time": 18.7932
    }
}