{
    "1.0": {
        "packet_latency": {
            "avg": 244.198,
            "min": 13.0,
            "max": 13.0
        },
        "network_latency": {
            "avg": 244.138,
            "min": 13.0,
            "max": 13.0
        },
        "flit_latency": {
            "avg": 238.673,
            "min": 13.0,
            "max": 13.0
        },
        "fragmentation": {
            "avg": 21.0587,
            "min": 0.0,
            "max": 0.0
        },
        "injected_packet_rate": {
            "avg": 0.00041355,
            "min": 7.1e-05,
            "max": 7.1e-05
        },
        "accepted_packet_rate": {
            "avg": 0.0004135,
            "min": 9.8e-05,
            "max": 9.8e-05
        },
        "injected_flit_rate": {
            "avg": 0.00164615,
            "min": 0.000116,
            "max": 0.000116
        },
        "accepted_flit_rate": {
            "avg": 0.0016457,
            "min": 0.00045,
            "max": 0.00045
        },
        "injected_packet_size": {
            "avg": 3.98053
        },
        "accepted_packet_size": {
            "avg": 3.97993
        },
        "hops": {
            "avg": 6.34281
        },
        "total_run_time_cycles": 1000000.0,
        "total_run_time": 21.9414
    }
}