{
    "1.0": {
        "packet_latency": {
            "avg": 165.758,
            "min": 48.0,
            "max": 48.0
        },
        "network_latency": {
            "avg": 165.758,
            "min": 48.0,
            "max": 48.0
        },
        "flit_latency": {
            "avg": 153.999,
            "min": 48.0,
            "max": 48.0
        },
        "fragmentation": {
            "avg": 24.7962,
            "min": 0.0,
            "max": 0.0
        },
        "injected_packet_rate": {
            "avg": 0.000184575,
            "min": 0.0,
            "max": 0.0
        },
        "accepted_packet_rate": {
            "avg": 0.0001845,
            "min": 0.0,
            "max": 0.0
        },
        "injected_flit_rate": {
            "avg": 0.000886975,
            "min": 0.0,
            "max": 0.0
        },
        "accepted_flit_rate": {
            "avg": 0.0008866,
            "min": 0.0,
            "max": 0.0
        },
        "injected_packet_size": {
            "avg": 4.8055
        },
        "accepted_packet_size": {
            "avg": 4.80542
        },
        "hops": {
            "avg": 4.5103
        },
        "total_run_time_cycles": 1000000.0,
        "total_run_time": 16.9697
    }
}