{
    "1.0": {
        "packet_latency": {
            "avg": 197.086,
            "min": 48.0,
            "max": 48.0
        },
        "network_latency": {
            "avg": 197.086,
            "min": 48.0,
            "max": 48.0
        },
        "flit_latency": {
            "avg": 185.066,
            "min": 48.0,
            "max": 48.0
        },
        "fragmentation": {
            "avg": 25.1368,
            "min": 0.0,
            "max": 0.0
        },
        "injected_packet_rate": {
            "avg": 0.000131825,
            "min": 0.0,
            "max": 0.0
        },
        "accepted_packet_rate": {
            "avg": 0.0001318,
            "min": 0.0,
            "max": 0.0
        },
        "injected_flit_rate": {
            "avg": 0.000641025,
            "min": 0.0,
            "max": 0.0
        },
        "accepted_flit_rate": {
            "avg": 0.000640825,
            "min": 0.0,
            "max": 0.0
        },
        "injected_packet_size": {
            "avg": 4.8627
        },
        "accepted_packet_size": {
            "avg": 4.8621
        },
        "hops": {
            "avg": 5.39985
        },
        "total_run_time_cycles": 1000000.0,
        "total_run_time": 690.491
    }
}