{
    "1.0": {
        "packet_latency": {
            "avg": 168.859,
            "min": 13.0,
            "max": 13.0
        },
        "network_latency": {
            "avg": 168.857,
            "min": 13.0,
            "max": 13.0
        },
        "flit_latency": {
            "avg": 165.69,
            "min": 13.0,
            "max": 13.0
        },
        "fragmentation": {
            "avg": 20.2284,
            "min": 0.0,
            "max": 0.0
        },
        "injected_packet_rate": {
            "avg": 0.0005831,
            "min": 7.1e-05,
            "max": 7.1e-05
        },
        "accepted_packet_rate": {
            "avg": 0.00058305,
            "min": 9.8e-05,
            "max": 9.8e-05
        },
        "injected_flit_rate": {
            "avg": 0.00231172,
            "min": 0.000119,
            "max": 0.000119
        },
        "accepted_flit_rate": {
            "avg": 0.00231165,
            "min": 0.00045,
            "max": 0.00045
        },
        "injected_packet_size": {
            "avg": 3.96454
        },
        "accepted_packet_size": {
            "avg": 3.96475
        },
        "hops": {
            "avg": 4.43011
        },
        "total_run_time_cycles": 1000000.0,
        "total_run_time": 20.7116
    }
}