{
    "1.0": {
        "packet_latency": {
            "avg": 251.177,
            "min": 83.0,
            "max": 83.0
        },
        "network_latency": {
            "avg": 251.177,
            "min": 83.0,
            "max": 83.0
        },
        "flit_latency": {
            "avg": 234.043,
            "min": 83.0,
            "max": 83.0
        },
        "fragmentation": {
            "avg": 24.811,
            "min": 0.0,
            "max": 0.0
        },
        "injected_packet_rate": {
            "avg": 6.24625e-05,
            "min": 0.0,
            "max": 0.0
        },
        "accepted_packet_rate": {
            "avg": 6.245e-05,
            "min": 0.0,
            "max": 0.0
        },
        "injected_flit_rate": {
            "avg": 0.000299862,
            "min": 0.0,
            "max": 0.0
        },
        "accepted_flit_rate": {
            "avg": 0.00029985,
            "min": 0.0,
            "max": 0.0
        },
        "injected_packet_size": {
            "avg": 4.80068
        },
        "accepted_packet_size": {
            "avg": 4.80144
        },
        "hops": {
            "avg": 6.94295
        },
        "total_run_time_cycles": 1000000.0,
        "total_run_time": 36.4965
    }
}