{
    "1.0": {
        "packet_latency": {
            "avg": 214.84,
            "min": 48.0,
            "max": 48.0
        },
        "network_latency": {
            "avg": 214.84,
            "min": 48.0,
            "max": 48.0
        },
        "flit_latency": {
            "avg": 199.672,
            "min": 48.0,
            "max": 48.0
        },
        "fragmentation": {
            "avg": 28.4227,
            "min": 0.0,
            "max": 0.0
        },
        "injected_packet_rate": {
            "avg": 0.000136975,
            "min": 0.0,
            "max": 0.0
        },
        "accepted_packet_rate": {
            "avg": 0.000136963,
            "min": 0.0,
            "max": 0.0
        },
        "injected_flit_rate": {
            "avg": 0.000730475,
            "min": 0.0,
            "max": 0.0
        },
        "accepted_flit_rate": {
            "avg": 0.000730362,
            "min": 0.0,
            "max": 0.0
        },
        "injected_packet_size": {
            "avg": 5.33291
        },
        "accepted_packet_size": {
            "avg": 5.33257
        },
        "hops": {
            "avg": 5.75303
        },
        "total_run_time_cycles": 1000000.0,
        "total_run_time": 829.695
    }
}